HDDFeaturesXS/__init__.py
HDDFeaturesXS/discernibleScore.py
HDDFeaturesXS/fastFeatureSelectionDS.py
HDDFeaturesXS/increDiscernibleScore.py
HDDFeaturesXS/increFeaSltDSFilterSam.py
HDDFeaturesXS/increFeatureSelectionDS.py
HDDFeaturesXS/partition_fold.py
HDDFeaturesXS-0.1.0.dist-info/METADATA
HDDFeaturesXS-0.1.0.dist-info/WHEEL
HDDFeaturesXS-0.1.0.dist-info/top_level.txt
HDDFeaturesXS-0.1.0.dist-info/RECORD
